crimestat3000/__init__.py
crimestat3000/helpers.py
crimestat3000/parse.py
crimestat3000-0.1.10.dist-info/LICENSE
crimestat3000-0.1.10.dist-info/METADATA
crimestat3000-0.1.10.dist-info/WHEEL
crimestat3000-0.1.10.dist-info/top_level.txt
crimestat3000-0.1.10.dist-info/RECORD
